odoo/addons/account_dashboard_banner/README.rst
odoo/addons/account_dashboard_banner/__init__.py
odoo/addons/account_dashboard_banner/__manifest__.py
odoo/addons/account_dashboard_banner/post_install.py
odoo/addons/account_dashboard_banner/i18n/account_dashboard_banner.pot
odoo/addons/account_dashboard_banner/i18n/de.po
odoo/addons/account_dashboard_banner/i18n/es.po
odoo/addons/account_dashboard_banner/i18n/fr.po
odoo/addons/account_dashboard_banner/i18n/it.po
odoo/addons/account_dashboard_banner/models/__init__.py
odoo/addons/account_dashboard_banner/models/account_dashboard_banner_cell.py
odoo/addons/account_dashboard_banner/readme/CONFIGURE.md
odoo/addons/account_dashboard_banner/readme/CONTRIBUTORS.md
odoo/addons/account_dashboard_banner/readme/DESCRIPTION.md
odoo/addons/account_dashboard_banner/readme/USAGE.md
odoo/addons/account_dashboard_banner/security/ir.model.access.csv
odoo/addons/account_dashboard_banner/static/description/account_dashboard_banner.png
odoo/addons/account_dashboard_banner/static/description/banner_cell_config.png
odoo/addons/account_dashboard_banner/static/description/cell_form_with_warning.png
odoo/addons/account_dashboard_banner/static/description/icon.png
odoo/addons/account_dashboard_banner/static/description/index.html
odoo/addons/account_dashboard_banner/static/src/views/account_dashboard_kanban_banner.esm.js
odoo/addons/account_dashboard_banner/static/src/views/account_dashboard_kanban_banner.xml
odoo/addons/account_dashboard_banner/tests/__init__.py
odoo/addons/account_dashboard_banner/tests/test_banner.py
odoo/addons/account_dashboard_banner/views/account_dashboard_banner_cell.xml
odoo/addons/account_dashboard_banner/views/account_journal_dashboard.xml
odoo_addon_account_dashboard_banner-18.0.1.2.0.5.dist-info/METADATA
odoo_addon_account_dashboard_banner-18.0.1.2.0.5.dist-info/WHEEL
odoo_addon_account_dashboard_banner-18.0.1.2.0.5.dist-info/top_level.txt
odoo_addon_account_dashboard_banner-18.0.1.2.0.5.dist-info/RECORD
