Metadata-Version: 2.1
Name: odoo-addon-account_dashboard_banner
Version: 18.0.1.2.0.5
Requires-Python: >=3.10
Requires-Dist: odoo==18.0.*
Summary: Add a configurable banner on the accounting dashboard
Home-page: https://github.com/OCA/account-financial-tools
License: AGPL-3
Author: Akretion,Odoo Community Association (OCA)
Author-email: support@odoo-community.org
Classifier: Programming Language :: Python
Classifier: Framework :: Odoo
Classifier: Framework :: Odoo :: 18.0
Classifier: License :: OSI Approved :: GNU Affero General Public License v3
Classifier: Development Status :: 4 - Beta
